tmui.py
tmui-0.1.1.dist-info/licenses/LICENSE
vendor/picotui/LICENSE
vendor/picotui/__init__.py
vendor/picotui/basewidget.py
vendor/picotui/context.py
vendor/picotui/defs.py
vendor/picotui/dialogs.py
vendor/picotui/editor.py
vendor/picotui/editorext.py
vendor/picotui/menu.py
vendor/picotui/screen.py
vendor/picotui/widgets.py
tmui-0.1.1.dist-info/METADATA
tmui-0.1.1.dist-info/WHEEL
tmui-0.1.1.dist-info/entry_points.txt
tmui-0.1.1.dist-info/top_level.txt
tmui-0.1.1.dist-info/RECORD
